Metadata-Version: 2.1
Name: inte3rstup
Version: 0.0.1
Summary: inte3rstup
Author-email: <inte3rstup@hotmail.com>
License: Eclipse Public License 2.0
Keywords: inte3rstup
